{
  "categorias":[
    {
      "id":1,
      "nombre":"luz",
      "frases":[
        {
          "id":1,
          "frase":"No olvides apagar la luz si no se está usando."
        },
        {
          "id":2,
          "frase":"Aprovecha la luz del sol al máiximo"
        },
        {
          "id":3,
          "frase":"Recuerda apagar el aire acondicionado si se van a abrir las ventanas."
        },
      ]
    },
     {
      "id":2,
      "nombre":"agua",
      "frases":[
        {
          "id":1,
          "frase":"Cierra el grifo del baño cuando no lo estés usando."
        },
        {
          "id":2,
          "frase":"No olvides apagar la luz si no se está usando."
        },
      ]
    }
  ]
}
